<?xml version="1.0" encoding="UTF-8"?>
<!DOCTYPE struts PUBLIC "-//Apache Software Foundation//DTD Struts Configuration 2.0//EN"
    "http://struts.apache.org/dtds/struts-2.0.dtd">

<struts>
	<!-- demo -->
	<package name="demo" extends="default" namespace="/demo">
		<action name="demoQuery" class="gridAction" method="queryEmp">
		</action>
		<action name="demoSave" class="gridAction" method="saveEmp">
		</action>
		<!-- <action name="ajaxAppQuery" class="appAction" method="ajaxQueryApps">
		</action>
		<action name="appAdd" class="appAction" method="addApp">
			<result name="success">/pages/app/appAdd.jsp</result>
		</action>	
		<action name="staChange" class="appAction" method="ajaxAppStaChange">
		</action>
		<action name="appForUpdate" class="appAction" method="appForUpdate">
			<result name="success">/pages/app/appUpdate.jsp</result>
		</action>
		<action name="appUpdate" class="appAction" method="appUpdate">
			<result name="success">/pages/app/appUpdate.jsp</result>
		</action>	 -->
	</package>
</struts>
